croydon/__init__.py
croydon/baseapp.py
croydon/command.py
croydon/config.py
croydon/context.py
croydon/db.py
croydon/decorators.py
croydon/errors.py
croydon/middleware.py
croydon/pagination.py
croydon/types.py
croydon/util.py
croydon/cache/__init__.py
croydon/cache/abc.py
croydon/cache/memcached.py
croydon/cache/no_cache.py
croydon/cache/req_local_cache.py
croydon/cache/simple.py
croydon/cache/trace_cache.py
croydon/commands/__init__.py
croydon/commands/init.py
croydon/models/__init__.py
croydon/models/base_model.py
croydon/models/counter.py
croydon/models/fields.py
croydon/models/index.py
croydon/models/meta_model.py
croydon/models/reference.py
croydon/models/storable_model.py
croydon/models/submodel.py
croydon/models/timestamped_model.py
croydon/project/__init__.py
croydon/project/models.py
croydon/project/util.py
croydon/project/templates/controller.py.tmpl
croydon/project/templates/model.py.tmpl
croydon/taskq/__init__.py
croydon/taskq/base_queue.py
croydon/taskq/mongo_queue.py
croydon/taskq/task.py
croydon/taskq/types.py
croydon/taskq/worker.py
croydon/templates/.shellrc.py
croydon/templates/application.toml.tmpl
croydon/templates/crcmd.py
croydon/templates/app/__init__.py
croydon/templates/app/application.py
croydon/templates/app/config.py
croydon/templates/app/extractors.py
croydon/templates/app/middleware.py
croydon/templates/app/commands/__init__.py
croydon/templates/app/commands/index.py
croydon/templates/app/commands/new.py
croydon/templates/app/commands/run.py
croydon/templates/app/commands/shell.py
croydon/templates/app/commands/tasks.py
croydon/templates/app/controllers/__init__.py
croydon/templates/app/controllers/api/__init__.py
croydon/templates/app/controllers/api/v1/__init__.py
croydon/templates/app/controllers/api/v1/account.py
croydon/templates/app/controllers/api/v1/response_types/__init__.py
croydon/templates/app/controllers/api/v1/response_types/account.py
croydon/templates/app/models/__init__.py
croydon/templates/app/models/session.py
croydon-0.25.0.dist-info/LICENSE
croydon-0.25.0.dist-info/METADATA
croydon-0.25.0.dist-info/WHEEL
croydon-0.25.0.dist-info/entry_points.txt
croydon-0.25.0.dist-info/top_level.txt
croydon-0.25.0.dist-info/RECORD
