Metadata-Version: 2.1
Name: croydon
Version: 0.25.0
Summary: a micro webframework based on fastapi and motor
Author-email: Pavel Vorobyev <aquavitale@yandex.ru>
License: MIT
Project-URL: Source, https://gitlab.com/viert/croydon
Keywords: fastapi,pymongo,mongodb,motor,asyncio
Requires-Python: >=3.11
License-File: LICENSE
Requires-Dist: fastapi[all] ==0.110.0
Requires-Dist: motor
Requires-Dist: pymongo
Requires-Dist: mongomock-motor
Requires-Dist: aiomcache
Requires-Dist: bcrypt
Requires-Dist: ipython
Requires-Dist: uvicorn
Requires-Dist: deprecation
Requires-Dist: jinja2
